rest_dataclasses/__init__.py
rest_dataclasses/__version__.py
rest_dataclasses/serializers.py
rest_dataclasses/utils.py
embedded_hermes_dataclasses-0.0.3.dist-info/LICENSE
embedded_hermes_dataclasses-0.0.3.dist-info/METADATA
embedded_hermes_dataclasses-0.0.3.dist-info/WHEEL
embedded_hermes_dataclasses-0.0.3.dist-info/top_level.txt
embedded_hermes_dataclasses-0.0.3.dist-info/RECORD
