Metadata-Version: 2.1
Name: embedded-hermes-dataclasses
Version: 0.0.3
Summary: Django REST Framework and dataclasses integration
Author: Serkan Hosca
Author-email: serkan@hosca.com
License: MIT
Keywords: dataclasses django rest framework drf rest_framework
Classifier: Development Status :: 3 - Alpha
Classifier: Environment :: Web Environment
Classifier: Framework :: Django
Classifier: Intended Audience :: Developers
Classifier: License :: OSI Approved :: MIT License
Classifier: Natural Language :: English
Classifier: Operating System :: OS Independent
Classifier: Programming Language :: Python :: 3.7
Classifier: Programming Language :: Python :: Implementation :: CPython
Classifier: Programming Language :: Python
Classifier: Topic :: Internet :: WWW/HTTP
License-File: LICENSE
Requires-Dist: django
Requires-Dist: djangorestframework
Requires-Dist: django-rest-enumfield
Requires-Dist: requests
